mad_whatsapp/__init__.py
mad_whatsapp/wap.py
mad_whatsapp-0.6.dist-info/LICENSE
mad_whatsapp-0.6.dist-info/METADATA
mad_whatsapp-0.6.dist-info/WHEEL
mad_whatsapp-0.6.dist-info/top_level.txt
mad_whatsapp-0.6.dist-info/RECORD
