Metadata-Version: 2.1
Name: mad-whatsapp
Version: 0.6
Summary: Parses Whatsapp conversations
Home-page: https://github.com/dobrescu/mad-whatsapp
Author: Dan Dobrescu
Author-email: d4n.dobrescu@gmail.com
License: MIT License
Keywords: parse whatsapp conversations
Classifier: Programming Language :: Python
Classifier: Programming Language :: Python :: 3
Classifier: License :: OSI Approved :: MIT License
Classifier: Operating System :: OS Independent
License-File: LICENSE
